{"_default": {"1": {"id": "xn4SOUSTCntY", "items": "find"}, "2": {"items": [{"index": 0, "name": "1dk_.gcode", "path": "1dk_.gcode", "sd": "false", "state": "Await", "timeLeft": 60.515274061985856}, {"index": 1, "name": "2dk_.gcode", "path": "2dk_.gcode", "sd": "false", "state": "Await", "timeLeft": 31.39699596306056}, {"index": 2, "name": "3dk_.gcode", "path": "3dk_.gcode", "sd": "false", "state": "Await", "timeLeft": 201.67166492333982}, {"index": 3, "name": "azzz__.gcode", "path": "azzz__.gcode", "sd": "false", "state": "Await", "timeLeft": 80.26315683523275}], "id": "aa1dcb94-122e-4b9c-b8ec-98e37bb15970", "updateTime": "2022-12-22 09:51:45.167125", "createTime": "2022-12-21 17:44:35.977851", "name": "aaaaaaaaaaaaaaa", "index": 1, "last": "last_queue"}, "3": {"items": [], "id": "7016e38d-75c7-4368-854c-f297a04c39a3", "updateTime": "2022-12-21 17:45:30.685254", "createTime": "2022-12-21 17:45:30.685285", "name": "QEQEQE222", "index": 0, "last": "none"}, "4": {"items": [{"index": 0, "name": "1dk_.gcode", "path": "1dk_.gcode", "sd": "false", "state": "Await", "timeLeft": 60.515274061985856}, {"index": 1, "name": "2dk_.gcode", "path": "2dk_.gcode", "sd": "false", "state": "Await", "timeLeft": 31.39699596306056}, {"index": 2, "name": "3dk_.gcode", "path": "3dk_.gcode", "sd": "false", "state": "Await", "timeLeft": 201.67166492333982}, {"index": 3, "name": "azzz__.gcode", "path": "azzz__.gcode", "sd": "false", "state": "Await", "timeLeft": 80.26315683523275}, {"index": 4, "name": "3dk_.gcode", "path": "3dk_.gcode", "sd": "false", "state": "Await", "timeLeft": 201.67166492333982}, {"index": 0, "name": "1dk_.gcode", "path": "1dk_.gcode", "sd": "false", "state": "Await", "timeLeft": 60.515274061985856}, {"index": 1, "name": "1dk_.gcode", "path": "1dk_.gcode", "sd": "false", "state": "Await", "timeLeft": 60.515274061985856}, {"index": 2, "name": "1dk_.gcode", "path": "1dk_.gcode", "sd": "false", "state": "Await", "timeLeft": 60.515274061985856}, {"index": 3, "name": "1dk_.gcode", "path": "1dk_.gcode", "sd": "false", "state": "Await", "timeLeft": 60.515274061985856}], "id": "eb794959-421f-4008-8dc8-ed336f16e925", "updateTime": "2022-12-22 09:46:52.059848", "createTime": "2022-12-22 09:46:52.059867", "name": "sssssssss", "index": 0, "last": "last_queue"}}}